{"cameraMode":{"drawMode":0,"name":"Shaded","section":"Shading Mode"},"sceneLighting":true,"audioPlay":false,"sceneViewState":{"m_AlwaysRefresh":false,"showFog":true,"showSkybox":true,"showFlares":true,"showImageEffects":true,"showParticleSystems":true,"showVisualEffectGraphs":true,"m_FxEnabled":true},"in2DMode":false,"pivot":{"x":27.76367950439453,"y":-6.821771621704102,"z":25.869709014892579},"rotation":{"x":0.022591667249798776,"y":0.9079112410545349,"z":-0.41562923789024355,"w":0.0493491068482399},"size":24.454389572143556,"orthographic":false}